MANIFEST.in
README.txt
setup.py
docs/HISTORY.txt
docs/LICENSE.txt
src/silva/__init__.py
src/silva.app.redirectlink.egg-info/PKG-INFO
src/silva.app.redirectlink.egg-info/SOURCES.txt
src/silva.app.redirectlink.egg-info/dependency_links.txt
src/silva.app.redirectlink.egg-info/namespace_packages.txt
src/silva.app.redirectlink.egg-info/not-zip-safe
src/silva.app.redirectlink.egg-info/requires.txt
src/silva.app.redirectlink.egg-info/top_level.txt
src/silva/app/__init__.py
src/silva/app/redirectlink/__init__.py
src/silva/app/redirectlink/configure.zcml
src/silva/app/redirectlink/ftesting.zcml
src/silva/app/redirectlink/interfaces.py
src/silva/app/redirectlink/link.png
src/silva/app/redirectlink/link.py
src/silva/app/redirectlink/link_templates/permanentredirecteditview.cpt
src/silva/app/redirectlink/tests/__init__.py
src/silva/app/redirectlink/tests/test_link.py