Metadata-Version: 1.1
Name: silva.app.redirectlink
Version: 3.0
Summary: Provides a link which does a permanent HTTP redirect to a moved Silva content
Home-page: https://github.com/silvacms/silva.app.redirectlink
Author: Sylvain Viollon
Author-email: info@infrae.com
License: BSD
Keywords: silva app redirect permanent http
Platform: UNKNOWN
Classifier: Framework :: Zope2
Classifier: License :: OSI Approved :: BSD License
Classifier: Programming Language :: Python
Classifier: Topic :: Software Development :: Libraries :: Python Modules
